{
  "schemaVersion": "public-math-ci-readback-v1",
  "status": "PASS_CI_SYNCED_AND_CLEAN",
  "result": "PASS",
  "failedStage": "none",
  "workflow": "Math CI Readback",
  "repository": "cobelinfuture-Kobel/taiwan-elementary-math-generator",
  "eventName": "push",
  "ref": "refs/heads/main",
  "refName": "main",
  "sha": "6b68fe2a75e4af18c47127f5b827623a4c96fdd7",
  "run": {
    "id": "29812080625",
    "number": "2591",
    "attempt": "1",
    "url": "https://github.com/cobelinfuture-Kobel/taiwan-elementary-math-generator/actions/runs/29812080625"
  },
  "checks": {
    "npmTestExitCode": {
      "expected": "0",
      "actual": "0"
    },
    "tests": {
      "expected": "auto-detected",
      "actual": "1987"
    },
    "pass": {
      "expected": "equal tests",
      "actual": "1987"
    },
    "fail": {
      "expected": "0",
      "actual": "0"
    },
    "workingTree": {
      "expected": "clean",
      "actual": "clean"
    }
  },
  "steps": {
    "checkout": "success",
    "setupNode": "success",
    "installDependencies": "success",
    "npmTest": "success",
    "verifyDynamicTestResult": "success",
    "gitStatus": "success",
    "verifyWorkingTree": "success"
  },
  "diagnostics": {
    "failingTestsExcerpt": "",
    "npmOutputTail": "d unknown codes\nok 1954 - createValidationResult rejects forbidden validator answer statuses and unknown codes\n  ---\n  duration_ms: 0.586361\n  ...\n# Subtest: validateNumericRange enforces integer and bound constraints\nok 1955 - validateNumericRange enforces integer and bound constraints\n  ---\n  duration_ms: 0.517121\n  ...\n# Subtest: validateDigitCount rejects leading zeroes and wrong digit lengths\nok 1956 - validateDigitCount rejects leading zeroes and wrong digit lengths\n  ---\n  duration_ms: 0.38718\n  ...\n# Subtest: validateSupportStatusCompatibility blocks items that overstate support\nok 1957 - validateSupportStatusCompatibility blocks items that overstate support\n  ---\n  duration_ms: 0.210942\n  ...\n# Subtest: validateNoFutureDomainLeakage detects decimals and future-domain markers\nok 1958 - validateNoFutureDomainLeakage detects decimals and future-domain markers\n  ---\n  duration_ms: 0.407668\n  ...\n# Subtest: validateUniqueAnswer fails obvious ambiguity and warns on borderline prompts\nok 1959 - validateUniqueAnswer fails obvious ambiguity and warns on borderline prompts\n  ---\n  duration_ms: 0.327129\n  ...\n# Subtest: validateSourceBoundary rejects generated items claiming source-backed or verified without evidence\nok 1960 - validateSourceBoundary rejects generated items claiming source-backed or verified without evidence\n  ---\n  duration_ms: 0.49462\n  ...\n# Subtest: validatePatternSpec runs structural checks only; accepts generic PatternSpec when no allow-list is provided\nok 1961 - validatePatternSpec runs structural checks only; accepts generic PatternSpec when no allow-list is provided\n  ---\n  duration_ms: 0.41368\n  ...\n# Subtest: validatePatternSpec allow-list mode rejects unknown patternSpecId\nok 1962 - validatePatternSpec allow-list mode rejects unknown patternSpecId\n  ---\n  duration_ms: 0.318622\n  ...\n# Subtest: validatePatternSpec catches missing hooks and empty validatorHooks\nok 1963 - validatePatternSpec catches missing hooks and empty validatorHooks\n  ---\n  duration_ms: 0.183822\n  ...\n# Subtest: validatePatternSpec allow-list mode rejects unknown hook names\nok 1964 - validatePatternSpec allow-list mode rejects unknown hook names\n  ---\n  duration_ms: 0.197397\n  ...\n# Subtest: validateAnswerStatus forbids validator assignment of verified and enforces computed prerequisites\nok 1965 - validateAnswerStatus forbids validator assignment of verified and enforces computed prerequisites\n  ---\n  duration_ms: 0.365139\n  ...\n# Subtest: validateDomainBoundary aggregates global core hooks and blocks unsupported visual items\nok 1966 - validateDomainBoundary aggregates global core hooks and blocks unsupported visual items\n  ---\n  duration_ms: 0.596459\n  ...\n# Subtest: H3 decomposes 7063 into place-value parts\nok 1967 - H3 decomposes 7063 into place-value parts\n  ---\n  duration_ms: 2.919601\n  ...\n# Subtest: H3 allows omitted zero place parts when explicitly allowed\nok 1968 - H3 allows omitted zero place parts when explicitly allowed\n  ---\n  duration_ms: 0.259232\n  ...\n# Subtest: H3 fails wrong hundreds, tens, or ones with place-value mismatch\nok 1969 - H3 fails wrong hundreds, tens, or ones with place-value mismatch\n  ---\n  duration_ms: 0.242\n  ...\n# Subtest: H3 digit-value subcase computes digit times place value\nok 1970 - H3 digit-value subcase computes digit times place value\n  ---\n  duration_ms: 0.423367\n  ...\n# Subtest: H3 digit-value subcase fails wrong candidate value\nok 1971 - H3 digit-value subcase fails wrong candidate value\n  ---\n  duration_ms: 0.255235\n  ...\n# Subtest: H4 composes 7 thousands, 0 hundreds, 6 tens, 3 ones into 7063\nok 1972 - H4 composes 7 thousands, 0 hundreds, 6 tens, 3 ones into 7063\n  ---\n  duration_ms: 0.543712\n  ...\n# Subtest: H4 normalizes omitted zero parts\nok 1973 - H4 normalizes omitted zero parts\n  ---\n  duration_ms: 0.351544\n  ...\n# Subtest: H4 supports count-based regrouping when allowed\nok 1974 - H4 supports count-based regrouping when allowed\n  ---\n  duration_ms: 0.285\n  ...\n# Subtest: H4 rejects regrouping when not allowed\nok 1975 - H4 rejects regrouping when not allowed\n  ---\n  duration_ms: 0.396468\n  ...\n# Subtest: H4 fails wrong candidate total with place-value mismatch\nok 1976 - H4 fails wrong candidate total with place-value mismatch\n  ---\n  duration_ms: 0.438485\n  ...\n# Subtest: H8 computes max and min for digits [0, 2, 5, 8]\nok 1977 - H8 computes max and min for digits [0, 2, 5, 8]\n  ---\n  duration_ms: 0.733684\n  ...\n# Subtest: H8 fails candidate with leading zero minimum\nok 1978 - H8 fails candidate with leading zero minimum\n  ---\n  duration_ms: 0.32276\n  ...\n# Subtest: H8 fails wrong max\nok 1979 - H8 fails wrong max\n  ---\n  duration_ms: 0.355862\n  ...\n# Subtest: H8 fails wrong min\nok 1980 - H8 fails wrong min\n  ---\n  duration_ms: 0.357836\n  ...\n# Subtest: H9 comparison passes for less-than relation\nok 1981 - H9 comparison passes for less-than relation\n  ---\n  duration_ms: 0.389985\n  ...\n# Subtest: H9 comparison passes for greater-than relation\nok 1982 - H9 comparison passes for greater-than relation\n  ---\n  duration_ms: 0.359539\n  ...\n# Subtest: H9 comparison passes for equal values\nok 1983 - H9 comparison passes for equal values\n  ---\n  duration_ms: 0.252129\n  ...\n# Subtest: H9 comparison fails wrong relation\nok 1984 - H9 comparison fails wrong relation\n  ---\n  duration_ms: 0.389194\n  ...\n# Subtest: scope guard: number-sense index does not export H5-H14 hooks\nok 1985 - scope guard: number-sense index does not export H5-H14 hooks\n  ---\n  duration_ms: 0.309496\n  ...\n# Subtest: scope guard: Chinese numeral parser files were not created\nok 1986 - scope guard: Chinese numeral parser files were not created\n  ---\n  duration_ms: 0.423197\n  ...\n# Subtest: scope guard: G3A U01 validator and pattern-pack files were not created\nok 1987 - scope guard: G3A U01 validator and pattern-pack files were not created\n  ---\n  duration_ms: 0.23124\n  ...\n1..1987\n# tests 1987\n# suites 0\n# pass 1987\n# fail 0\n# cancelled 0\n# skipped 0\n# todo 0\n# duration_ms 81951.786986\n",
    "failureContext": ""
  },
  "updatedAt": "2026-07-21T07:54:39.125864Z"
}
