{
  "schemaVersion": "public-math-ci-readback-v1",
  "status": "PASS_CI_SYNCED_AND_CLEAN",
  "result": "PASS",
  "failedStage": "none",
  "workflow": "Math CI Readback",
  "repository": "cobelinfuture-Kobel/taiwan-elementary-math-generator",
  "eventName": "push",
  "ref": "refs/heads/main",
  "refName": "main",
  "sha": "0ed8b9803896f7f02d327c06f092bad1c8c41a9a",
  "run": {
    "id": "28880626974",
    "number": "496",
    "attempt": "1",
    "url": "https://github.com/cobelinfuture-Kobel/taiwan-elementary-math-generator/actions/runs/28880626974"
  },
  "checks": {
    "npmTestExitCode": {
      "expected": "0",
      "actual": "0"
    },
    "tests": {
      "expected": "auto-detected",
      "actual": "427"
    },
    "pass": {
      "expected": "equal tests",
      "actual": "427"
    },
    "fail": {
      "expected": "0",
      "actual": "0"
    },
    "workingTree": {
      "expected": "clean",
      "actual": "clean"
    }
  },
  "steps": {
    "checkout": "success",
    "setupNode": "success",
    "installDependencies": "success",
    "npmTest": "success",
    "verifyDynamicTestResult": "success",
    "gitStatus": "success",
    "verifyWorkingTree": "success"
  },
  "diagnostics": {
    "failingTestsExcerpt": "",
    "npmOutputTail": "n validator answer statuses and unknown codes\nok 394 - createValidationResult rejects forbidden validator answer statuses and unknown codes\n  ---\n  duration_ms: 0.407391\n  ...\n# Subtest: validateNumericRange enforces integer and bound constraints\nok 395 - validateNumericRange enforces integer and bound constraints\n  ---\n  duration_ms: 0.298219\n  ...\n# Subtest: validateDigitCount rejects leading zeroes and wrong digit lengths\nok 396 - validateDigitCount rejects leading zeroes and wrong digit lengths\n  ---\n  duration_ms: 0.34154\n  ...\n# Subtest: validateSupportStatusCompatibility blocks items that overstate support\nok 397 - validateSupportStatusCompatibility blocks items that overstate support\n  ---\n  duration_ms: 0.166538\n  ...\n# Subtest: validateNoFutureDomainLeakage detects decimals and future-domain markers\nok 398 - validateNoFutureDomainLeakage detects decimals and future-domain markers\n  ---\n  duration_ms: 0.307278\n  ...\n# Subtest: validateUniqueAnswer fails obvious ambiguity and warns on borderline prompts\nok 399 - validateUniqueAnswer fails obvious ambiguity and warns on borderline prompts\n  ---\n  duration_ms: 0.272192\n  ...\n# Subtest: validateSourceBoundary rejects generated items claiming source-backed or verified without evidence\nok 400 - validateSourceBoundary rejects generated items claiming source-backed or verified without evidence\n  ---\n  duration_ms: 0.313907\n  ...\n# Subtest: validatePatternSpec runs structural checks only; accepts generic PatternSpec when no allow-list is provided\nok 401 - validatePatternSpec runs structural checks only; accepts generic PatternSpec when no allow-list is provided\n  ---\n  duration_ms: 0.350851\n  ...\n# Subtest: validatePatternSpec allow-list mode rejects unknown patternSpecId\nok 402 - validatePatternSpec allow-list mode rejects unknown patternSpecId\n  ---\n  duration_ms: 0.265333\n  ...\n# Subtest: validatePatternSpec catches missing hooks and empty validatorHooks\nok 403 - validatePatternSpec catches missing hooks and empty validatorHooks\n  ---\n  duration_ms: 0.143516\n  ...\n# Subtest: validatePatternSpec allow-list mode rejects unknown hook names\nok 404 - validatePatternSpec allow-list mode rejects unknown hook names\n  ---\n  duration_ms: 0.154134\n  ...\n# Subtest: validateAnswerStatus forbids validator assignment of verified and enforces computed prerequisites\nok 405 - validateAnswerStatus forbids validator assignment of verified and enforces computed prerequisites\n  ---\n  duration_ms: 0.27005\n  ...\n# Subtest: validateDomainBoundary aggregates global core hooks and blocks unsupported visual items\nok 406 - validateDomainBoundary aggregates global core hooks and blocks unsupported visual items\n  ---\n  duration_ms: 0.527701\n  ...\n# Subtest: H3 decomposes 7063 into place-value parts\nok 407 - H3 decomposes 7063 into place-value parts\n  ---\n  duration_ms: 2.766897\n  ...\n# Subtest: H3 allows omitted zero place parts when explicitly allowed\nok 408 - H3 allows omitted zero place parts when explicitly allowed\n  ---\n  duration_ms: 0.239998\n  ...\n# Subtest: H3 fails wrong hundreds, tens, or ones with place-value mismatch\nok 409 - H3 fails wrong hundreds, tens, or ones with place-value mismatch\n  ---\n  duration_ms: 0.229904\n  ...\n# Subtest: H3 digit-value subcase computes digit times place value\nok 410 - H3 digit-value subcase computes digit times place value\n  ---\n  duration_ms: 0.343545\n  ...\n# Subtest: H3 digit-value subcase fails wrong candidate value\nok 411 - H3 digit-value subcase fails wrong candidate value\n  ---\n  duration_ms: 0.223834\n  ...\n# Subtest: H4 composes 7 thousands, 0 hundreds, 6 tens, 3 ones into 7063\nok 412 - H4 composes 7 thousands, 0 hundreds, 6 tens, 3 ones into 7063\n  ---\n  duration_ms: 0.51693\n  ...\n# Subtest: H4 normalizes omitted zero parts\nok 413 - H4 normalizes omitted zero parts\n  ---\n  duration_ms: 0.316404\n  ...\n# Subtest: H4 supports count-based regrouping when allowed\nok 414 - H4 supports count-based regrouping when allowed\n  ---\n  duration_ms: 0.245354\n  ...\n# Subtest: H4 rejects regrouping when not allowed\nok 415 - H4 rejects regrouping when not allowed\n  ---\n  duration_ms: 0.370484\n  ...\n# Subtest: H4 fails wrong candidate total with place-value mismatch\nok 416 - H4 fails wrong candidate total with place-value mismatch\n  ---\n  duration_ms: 0.335627\n  ...\n# Subtest: H8 computes max and min for digits [0, 2, 5, 8]\nok 417 - H8 computes max and min for digits [0, 2, 5, 8]\n  ---\n  duration_ms: 0.680566\n  ...\n# Subtest: H8 fails candidate with leading zero minimum\nok 418 - H8 fails candidate with leading zero minimum\n  ---\n  duration_ms: 0.328341\n  ...\n# Subtest: H8 fails wrong max\nok 419 - H8 fails wrong max\n  ---\n  duration_ms: 0.330736\n  ...\n# Subtest: H8 fails wrong min\nok 420 - H8 fails wrong min\n  ---\n  duration_ms: 0.303466\n  ...\n# Subtest: H9 comparison passes for less-than relation\nok 421 - H9 comparison passes for less-than relation\n  ---\n  duration_ms: 0.373832\n  ...\n# Subtest: H9 comparison passes for greater-than relation\nok 422 - H9 comparison passes for greater-than relation\n  ---\n  duration_ms: 0.297002\n  ...\n# Subtest: H9 comparison passes for equal values\nok 423 - H9 comparison passes for equal values\n  ---\n  duration_ms: 0.199632\n  ...\n# Subtest: H9 comparison fails wrong relation\nok 424 - H9 comparison fails wrong relation\n  ---\n  duration_ms: 0.359458\n  ...\n# Subtest: scope guard: number-sense index does not export H5-H14 hooks\nok 425 - scope guard: number-sense index does not export H5-H14 hooks\n  ---\n  duration_ms: 0.218544\n  ...\n# Subtest: scope guard: Chinese numeral parser files were not created\nok 426 - scope guard: Chinese numeral parser files were not created\n  ---\n  duration_ms: 0.322522\n  ...\n# Subtest: scope guard: G3A U01 validator and pattern-pack files were not created\nok 427 - scope guard: G3A U01 validator and pattern-pack files were not created\n  ---\n  duration_ms: 0.192042\n  ...\n1..427\n# tests 427\n# suites 0\n# pass 427\n# fail 0\n# cancelled 0\n# skipped 0\n# todo 0\n# duration_ms 3561.938008\n",
    "failureContext": ""
  },
  "updatedAt": "2026-07-07T16:05:28.048748Z"
}
